{
  "os": "Linux-6.8.0-49-generic-x86_64-with-glibc2.39",
  "python": "CPython 3.12.3",
  "startedAt": "2025-09-03T12:35:09.651525Z",
  "args": [
    "--config",
    "configs/config.yaml"
  ],
  "program": "/home/rigers/Documents/GitHub/ML-correlator/GNN/one_run_simple.py",
  "codePath": "GNN/one_run_simple.py",
  "git": {
    "remote": "https://github.com/GabrieleDian/ML-correlator.git",
    "commit": "c1a681d25078aeaaab2764b4246c22d4860555ce"
  },
  "email": "aliajrigers@gmail.com",
  "root": "/home/rigers/Documents/GitHub/ML-correlator/GNN",
  "host": "rigersaliaj",
  "executable": "/home/rigers/Documents/GitHub/Human-Learning/.venv/bin/python",
  "codePathLocal": "one_run_simple.py",
  "cpu_count": 4,
  "cpu_count_logical": 8,
  "disk": {
    "/": {
      "total": "250375106560",
      "used": "206832488448"
    }
  },
  "memory": {
    "total": "16569896960"
  },
  "cpu": {
    "count": 4,
    "countLogical": 8
  }
}